yprov4ml/__init__.py
yprov4ml/constants.py
yprov4ml/dot2svg.py
yprov4ml/logging_aux.py
yprov4ml/prov2dot.py
yprov4ml/yprov4ml.py
yprov4ml/datamodel/__init__.py
yprov4ml/datamodel/artifact_data.py
yprov4ml/datamodel/attribute_type.py
yprov4ml/datamodel/compressor_type.py
yprov4ml/datamodel/context.py
yprov4ml/datamodel/metric_data.py
yprov4ml/datamodel/metric_type.py
yprov4ml/datamodel/prov4ml_data.py
yprov4ml/loggers/__init__.py
yprov4ml/loggers/itwinai_logger.py
yprov4ml/loggers/prov4ml_itwinai_logger.py
yprov4ml/loggers/prov4ml_logger.py
yprov4ml/provenance/__init__.py
yprov4ml/provenance/provenance_graph.py
yprov4ml/utils/__init__.py
yprov4ml/utils/energy_utils.py
yprov4ml/utils/file_utils.py
yprov4ml/utils/flops_utils.py
yprov4ml/utils/funcs.py
yprov4ml/utils/prov_getters.py
yprov4ml/utils/prov_utils.py
yprov4ml/utils/system_utils.py
yprov4ml/utils/time_utils.py
yprov4ml/wrappers/__init__.py
yprov4ml/wrappers/indexed_dataset.py
yprov4ml-2.0.8.dist-info/licenses/LICENSE
yprov4ml-2.0.8.dist-info/METADATA
yprov4ml-2.0.8.dist-info/WHEEL
yprov4ml-2.0.8.dist-info/top_level.txt
yprov4ml-2.0.8.dist-info/RECORD
