Metadata-Version: 2.4
Name: yprov4ml
Version: 2.0.8
Summary: Part of the yProv suite, and provides a unified interface for logging and tracking provenance information in machine learning experiments, both on distributed as well as large scale experiments.
Author-email: Gabriele Padovani <gabriele.padovani@unitn.it>
License:                     GNU GENERAL PUBLIC LICENSE
Project-URL: Homepage, https://github.com/HPCI-Lab/yProvML
Project-URL: Issues, https://github.com/HPCI-Lab/yProvML/issues
Classifier: Programming Language :: Python :: 3
Classifier: Operating System :: OS Independent
Requires-Python: >=3.9
License-File: LICENSE
Requires-Dist: codecarbon>=2.8
Requires-Dist: fvcore
Requires-Dist: geocoder
Requires-Dist: gpustat
Requires-Dist: GPUtil
Requires-Dist: lightning
Requires-Dist: netCDF4
Requires-Dist: numpy
Requires-Dist: nvitop
Requires-Dist: pandas
Requires-Dist: psutil
Requires-Dist: pydot
Requires-Dist: torch
Requires-Dist: torchvision
Requires-Dist: tqdm
Requires-Dist: typing_extensions
Requires-Dist: rocrate
Requires-Dist: aenum
Requires-Dist: prov
Requires-Dist: zarr
Requires-Dist: lxml
Requires-Dist: rdflib<7
Requires-Dist: nvidia-ml-py
Provides-Extra: apple
Requires-Dist: apple_gpu==0.3.*; extra == "apple"
Provides-Extra: amd
Requires-Dist: pyamdgpuinfo==2.1.*; extra == "amd"
Provides-Extra: nvidia
Requires-Dist: nvitop==1.3.*; extra == "nvidia"
Dynamic: license-file
